{
  "name": "report",
  "base": "PersistedModel",
  "idInjection": false,
  "options": {
    "validateUpsert": true
  },
  "properties": {
    "DESCRIPTION": {
      "type": "string",
      "required": true,
      "id": true
    },
    "YEAR": {
      "type": "string",
      "required": true
    },
    "PERCENTAGE": {
      "type": "string",
      "required": true
    },
    "TW1": {
      "type": "string",
      "required": true
    },
    "TW2": {
      "type": "string",
      "required": true
    },
    "TW3": {
      "type": "string",
      "required": true
    },
    "TW4": {
      "type": "string",
      "required": true
    }
  },
  "validations": [],
  "relations": {},
  "acls": [],
  "methods": {}
}
